CHANGES.txt
CONTRIBUTORS.txt
LICENSE.txt
MANIFEST.in
README.rst
setup.py
qhonuskan_votes/__init__.py
qhonuskan_votes/compat.py
qhonuskan_votes/models.py
qhonuskan_votes/urls.py
qhonuskan_votes/utils.py
qhonuskan_votes/views.py
qhonuskan_votes.egg-info/PKG-INFO
qhonuskan_votes.egg-info/SOURCES.txt
qhonuskan_votes.egg-info/dependency_links.txt
qhonuskan_votes.egg-info/not-zip-safe
qhonuskan_votes.egg-info/requires.txt
qhonuskan_votes.egg-info/top_level.txt
qhonuskan_votes/static/default_buttons.css
qhonuskan_votes/templates/qhonuskan/vote_buttons.html
qhonuskan_votes/templates/qhonuskan/voting_js.html
qhonuskan_votes/templatetags/__init__.py
qhonuskan_votes/templatetags/qhonuskan_votes.py
requirements/global.txt