Metadata-Version: 1.1
Name: qhonuskan-votes
Version: 0.2
Summary: Easy to use reddit like voting system for django models.
Home-page: https://github.com/linkfloyd/qhonuskan-votes
Author: Mirat Can Bayrak
Author-email: miratcanbayrak@gmail.com
License: GPL
Platform: UNKNOWN
Classifier: Development Status :: 4 - Beta
Classifier: Intended Audience :: Developers
Classifier: Programming Language :: Python
Classifier: Operating System :: OS Independent
Classifier: Environment :: Web Environment
Classifier: Framework :: Django
